gae_sdk_path_fixer/__init__.py
gae_sdk_path_fixer/download_gae_sdk.py
gae_sdk_path_fixer-0.1.2.dist-info/METADATA
gae_sdk_path_fixer-0.1.2.dist-info/WHEEL
gae_sdk_path_fixer-0.1.2.dist-info/entry_points.txt
gae_sdk_path_fixer-0.1.2.dist-info/top_level.txt
gae_sdk_path_fixer-0.1.2.dist-info/RECORD
