Metadata-Version: 2.1
Name: gae-sdk-path-fixer
Version: 0.1.2
Summary: GAE SDK Path Fixer: detect AppEngine SDK and fix Python sys.path
Home-page: https://github.com/kkroening/gae-sdk-path-fixer
Author: Karl Kroening
Author-email: karlk@kralnet.us
License: UNKNOWN
Platform: UNKNOWN
